torchextras/__init__.py
torchextras-0.0.1.dist-info/LICENSE
torchextras-0.0.1.dist-info/METADATA
torchextras-0.0.1.dist-info/WHEEL
torchextras-0.0.1.dist-info/top_level.txt
torchextras-0.0.1.dist-info/RECORD
